pulpcore/__init__.py
pulpcore/client/__init__.py
pulpcore/client/pulp_service/__init__.py
pulpcore/client/pulp_service/api_client.py
pulpcore/client/pulp_service/api_response.py
pulpcore/client/pulp_service/configuration.py
pulpcore/client/pulp_service/exceptions.py
pulpcore/client/pulp_service/py.typed
pulpcore/client/pulp_service/rest.py
pulpcore/client/pulp_service/api/__init__.py
pulpcore/client/pulp_service/api/api_create_domain_api.py
pulpcore/client/pulp_service/api/api_debug_auth_header_api.py
pulpcore/client/pulp_service/api/api_debug_database_triggers_api.py
pulpcore/client/pulp_service/api/api_debug_release_task_locks_api.py
pulpcore/client/pulp_service/api/api_rds_connection_tests_api.py
pulpcore/client/pulp_service/api/api_test_random_lock_tasks_api.py
pulpcore/client/pulp_service/api/api_test_tasks_api.py
pulpcore/client/pulp_service/api/contentguards_feature_api.py
pulpcore/client/pulp_service/api/tasks_api.py
pulpcore/client/pulp_service/api/vuln_report_service_api.py
pulpcore/client/pulp_service/models/__init__.py
pulpcore/client/pulp_service/models/async_operation_response.py
pulpcore/client/pulp_service/models/domain.py
pulpcore/client/pulp_service/models/domain_response.py
pulpcore/client/pulp_service/models/my_permissions_response.py
pulpcore/client/pulp_service/models/nested_role.py
pulpcore/client/pulp_service/models/nested_role_response.py
pulpcore/client/pulp_service/models/object_roles_response.py
pulpcore/client/pulp_service/models/paginated_task_response_list.py
pulpcore/client/pulp_service/models/paginatedservice_feature_content_guard_response_list.py
pulpcore/client/pulp_service/models/paginatedservice_vulnerability_report_response_list.py
pulpcore/client/pulp_service/models/patchedservice_feature_content_guard.py
pulpcore/client/pulp_service/models/progress_report_response.py
pulpcore/client/pulp_service/models/service_feature_content_guard.py
pulpcore/client/pulp_service/models/service_feature_content_guard_response.py
crc_pulp_service_client-20260130.1.dist-info/METADATA
crc_pulp_service_client-20260130.1.dist-info/WHEEL
crc_pulp_service_client-20260130.1.dist-info/top_level.txt
crc_pulp_service_client-20260130.1.dist-info/RECORD
